pyBKT.libs/libgomp-65f46eca.so.1.0.0
pyBKT-1.4.1.dist-info/WHEEL
pyBKT-1.4.1.dist-info/LICENSE
pyBKT-1.4.1.dist-info/top_level.txt
pyBKT-1.4.1.dist-info/METADATA
pyBKT-1.4.1.dist-info/RECORD
pyBKT/__init__.py
pyBKT/fit/EM_fit.py
pyBKT/fit/predict_onestep.py
pyBKT/fit/__init__.py
pyBKT/fit/E_step.cpython-36m-i386-linux-gnu.so
pyBKT/fit/M_step.py
pyBKT/fit/predict_onestep_states.cpython-36m-i386-linux-gnu.so
pyBKT/generate/synthetic_data_helper.cpython-36m-i386-linux-gnu.so
pyBKT/generate/random_model_uni.py
pyBKT/generate/synthetic_data.py
pyBKT/generate/random_model.py
pyBKT/generate/__init__.py
pyBKT/util/print_dot.py
pyBKT/util/metrics.py
pyBKT/util/check_data.py
pyBKT/util/__init__.py
pyBKT/util/dirrnd.py
pyBKT/util/crossvalidate.py
pyBKT/util/data_helper.py
pyBKT/models/Roster.py
pyBKT/models/__init__.py
pyBKT/models/Model.py
