Metadata-Version: 2.1
Name: pyBKT
Version: 1.4.1
Summary: PyBKT - Python Implentation of Bayesian Knowledge Tracing
Home-page: https://github.com/CAHLR/pyBKT
Author: Zachary Pardos, Anirudhan Badrinath, Matthew Jade Johnson, Christian Garay
Author-email: zp@berkeley.edu, abadrinath@berkeley.edu, mattjj@csail.mit.edu, c.garay@berkeley.edu
License: MIT
Download-URL: https://github.com/CAHLR/pyBKT/archive/1.0.tar.gz
Keywords: BKT,Bayesian Knowledge Tracing,Bayesian Network,Hidden Markov Model,Intelligent Tutoring Systems,Adaptive Learning
Platform: UNKNOWN
Classifier: Programming Language :: Python :: 3.5
Classifier: Programming Language :: Python :: 3.6
Classifier: Programming Language :: Python :: 3.7
Classifier: Programming Language :: Python :: 3.8
Classifier: License :: OSI Approved :: MIT License
Classifier: Operating System :: OS Independent
License-File: LICENSE
Requires-Dist: numpy
Requires-Dist: scikit-learn
Requires-Dist: pandas
Requires-Dist: requests
